pycddl/__init__.py
pycddl/pycddl.cpython-310-darwin.so
pycddl-0.6.4.dist-info/RECORD
pycddl-0.6.4.dist-info/WHEEL
pycddl-0.6.4.dist-info/METADATA
pycddl-0.6.4.dist-info/licenses/LICENSE
