Metadata-Version: 2.4
Name: pycddl
Version: 0.6.4
License-File: LICENSE
Summary: Deserialize CBOR and/or do CDDL schema validation
Home-Page: https://gitlab.com/tahoe-lafs/pycddl
Author: Tahoe-LAFS project
License: MIT
Requires-Python: >=3.8
